<annotation>
  <folder>train</folder>
  <filename>argonian24</filename>
  <path>C:\Users\Marko\projects\images\train\argonian24.jpg</path>
  <source>
    <database>Unknown</database>
  </source>
  <size>
    <width>300</width>
    <height>500</height>
    <depth>3</depth>
  </size>
  <segmented>0</segmented>
  <object>
    <name>argonian</name>
    <pose>Unspecified</pose>
    <truncated>0</truncated>
    <difficult>0</difficult>
    <bndbox>
      <xmin>113</xmin>
      <ymin>46</ymin>
      <xmax>175</xmax>
      <ymax>102</ymax>
    </bndbox>
  </object>
</annotation>
